turion/__init__.py
turion/__main__.py
turion/predict.py
turion/turion.py
turion/visualize.py
turion-0.0.2.dist-info/METADATA
turion-0.0.2.dist-info/WHEEL
turion-0.0.2.dist-info/RECORD
